README.rst
setup.py
ajedrez_asir.egg-info/PKG-INFO
ajedrez_asir.egg-info/SOURCES.txt
ajedrez_asir.egg-info/dependency_links.txt
ajedrez_asir.egg-info/entry_points.txt
ajedrez_asir.egg-info/requires.txt
ajedrez_asir.egg-info/top_level.txt
chessasir/__init__.py
chessasir/game.py
chessasir/moves.py
chessasir/player.py
chessasir/server.py
chessasir/chess-client/chess.css
chessasir/chess-client/chess.js
chessasir/chess-client/game.js
chessasir/chess-client/index.html
chessasir/chess-client/main.js
chessasir/chess-client/server.js
chessasir/chess-client/widget.js