Metadata-Version: 1.1
Name: ajedrez-asir
Version: 0.1
Summary: ajedrez online para ASIR
Home-page: https://github.com/dotoscat/ajedrez-online
Author: Oscar (dotoscat) Triano
Author-email: UNKNOWN
License: AGPL-3.0
Keywords: chess server
Platform: UNKNOWN
Classifier: Development Status :: 3 - Alpha
Classifier: Framework :: AsyncIO
Classifier: Intended Audience :: Developers
Classifier: License :: OSI Approved :: GNU Affero General Public License v3 or later (AGPLv3+)
Classifier: Programming Language :: JavaScript
Classifier: Programming Language :: Python :: 3 :: Only
Classifier: Topic :: Games/Entertainment :: Board Games
